{"cameraMode":{"drawMode":0,"name":"Shaded","section":"Shading Mode"},"sceneLighting":true,"audioPlay":false,"sceneViewState":{"showFog":true,"showMaterialUpdate":false,"showSkybox":true,"showFlares":true,"showImageEffects":true,"showParticleSystems":true},"in2DMode":false,"pivot":{"x":170.24459838867188,"y":63.674346923828128,"z":-56.78472900390625},"rotation":{"x":0.025487950071692468,"y":0.026987947523593904,"z":-0.000688341970089823,"w":0.9993105530738831},"size":1.7636663913726807,"orthographic":false}